deccan_toon/__init__.py
deccan_toon/decoder.py
deccan_toon/encoder.py
deccan_toon/errors.py
deccan_toon-0.2.0.dist-info/METADATA
deccan_toon-0.2.0.dist-info/WHEEL
deccan_toon-0.2.0.dist-info/licenses/LICENSE
deccan_toon-0.2.0.dist-info/RECORD
