Metadata-Version: 2.4
Name: deccan-toon
Version: 0.2.0
Summary: Battling JSON bloat with Pythonic elegance. A high-efficiency TOON serializer.
License: MIT
License-File: LICENSE
Keywords: toon,json,llm,ai,serialization,agentic-web,token-optimization
Author: Saurabh Dugdhe
Author-email: saurabhdugdhe18@gmail.com
Requires-Python: >=3.10,<4.0
Classifier: License :: OSI Approved :: MIT License
Classifier: Operating System :: OS Independent
Classifier: Programming Language :: Python :: 3
Classifier: Programming Language :: Python :: 3.10
Classifier: Programming Language :: Python :: 3.11
Classifier: Programming Language :: Python :: 3.12
Classifier: Programming Language :: Python :: 3.13
Classifier: Programming Language :: Python :: 3.14
Project-URL: Homepage, https://github.com/DeccanTensor/toon-py
Project-URL: Repository, https://github.com/DeccanTensor/toon-py
